{
  "ultimaAtualizacao": "2025-10-06T18:15:13.985Z",
  "total": 22,
  "produtos": [
    {
      "id": "0301",
      "titulo": "03/01 Rádio 01",
      "tecnica": "Impressão offset em papel couché transferida para EVA estampado, chapa união, porcas e parafusos. ",
      "dimensao": "57 x 18 x 10 cm",
      "preco": 150,
      "status": "disponível",
      "disponivel": true,
      "imagens": [
        {
          "thumb": "https://betshoptv.com/img/tmb/03-01a.avif",
          "otm": "https://betshoptv.com/img/otm/03-01a.avif",
          "fallback": "https://betshoptv.com/img/fallback/03-01a.jpg"
        },
        {
          "thumb": "https://betshoptv.com/img/tmb/03-01b.avif",
          "otm": "https://betshoptv.com/img/otm/03-01b.avif",
          "fallback": "https://betshoptv.com/img/fallback/03-01b.jpg"
        },
        {
          "thumb": "https://betshoptv.com/img/tmb/03-01c.avif",
          "otm": "https://betshoptv.com/img/otm/03-01c.avif",
          "fallback": "https://betshoptv.com/img/fallback/03-01c.jpg"
        },
        {
          "thumb": "https://betshoptv.com/img/tmb/03-01d.avif",
          "otm": "https://betshoptv.com/img/otm/03-01d.avif",
          "fallback": "https://betshoptv.com/img/fallback/03-01d.jpg"
        }
      ]
    },
    {
      "id": "0302",
      "titulo": "03/02 Câmera fotográfica 01",
      "tecnica": "Impressão offset em papel couché transferida para EVA estampado e parafusos.",
      "dimensao": "21 x 21 x 09 cm",
      "preco": 150,
      "status": "disponível",
      "disponivel": true,
      "imagens": [
        {
          "thumb": "https://betshoptv.com/img/tmb/03-02a.avif",
          "otm": "https://betshoptv.com/img/otm/03-02a.avif",
          "fallback": "https://betshoptv.com/img/fallback/03-02a.jpg"
        },
        {
          "thumb": "https://betshoptv.com/img/tmb/03-02b.avif",
          "otm": "https://betshoptv.com/img/otm/03-02b.avif",
          "fallback": "https://betshoptv.com/img/fallback/03-02b.jpg"
        },
        {
          "thumb": "https://betshoptv.com/img/tmb/03-02c.avif",
          "otm": "https://betshoptv.com/img/otm/03-02c.avif",
          "fallback": "https://betshoptv.com/img/fallback/03-02c.jpg"
        }
      ]
    },
    {
      "id": "0303",
      "titulo": "03/03 Polaroid 01",
      "tecnica": "Impressão offset em papel couché transferida para EVA estampado, braçadeira e parafusos.",
      "dimensao": "23 x 25 x 08 cm",
      "preco": 150,
      "status": "em análise",
      "disponivel": false,
      "imagens": [
        {
          "thumb": "https://betshoptv.com/img/tmb/03-03a.avif",
          "otm": "https://betshoptv.com/img/otm/03-03a.avif",
          "fallback": "https://betshoptv.com/img/fallback/03-03a.jpg"
        },
        {
          "thumb": "https://betshoptv.com/img/tmb/03-03b.avif",
          "otm": "https://betshoptv.com/img/otm/03-03b.avif",
          "fallback": "https://betshoptv.com/img/fallback/03-03b.jpg"
        },
        {
          "thumb": "https://betshoptv.com/img/tmb/03-03c.avif",
          "otm": "https://betshoptv.com/img/otm/03-03c.avif",
          "fallback": "https://betshoptv.com/img/fallback/03-03c.jpg"
        }
      ]
    },
    {
      "id": "0304",
      "titulo": "03/04 Auto Rádio 01",
      "tecnica": "Impressão offset em papel couché transferida para EVA estampado, tinta acrílica e escápulas.",
      "dimensao": "27 x 18 x 06 cm",
      "preco": 150,
      "status": "em análise",
      "disponivel": false,
      "imagens": [
        {
          "thumb": "https://betshoptv.com/img/tmb/03-04a.avif",
          "otm": "https://betshoptv.com/img/otm/03-04a.avif",
          "fallback": "https://betshoptv.com/img/fallback/03-04a.jpg"
        },
        {
          "thumb": "https://betshoptv.com/img/tmb/03-04b.avif",
          "otm": "https://betshoptv.com/img/otm/03-04b.avif",
          "fallback": "https://betshoptv.com/img/fallback/03-04b.jpg"
        }
      ]
    },
    {
      "id": "0305",
      "titulo": "03/05 TV Portátil 01",
      "tecnica": "Impressão offset em papel couché transferida para EVA estampado e parafusos.",
      "dimensao": "25 x 21 x 07 cm",
      "preco": 200,
      "status": "disponível",
      "disponivel": true,
      "imagens": [
        {
          "thumb": "https://betshoptv.com/img/tmb/03-05a.avif",
          "otm": "https://betshoptv.com/img/otm/03-05a.avif",
          "fallback": "https://betshoptv.com/img/fallback/03-05a.jpg"
        },
        {
          "thumb": "https://betshoptv.com/img/tmb/03-05b.avif",
          "otm": "https://betshoptv.com/img/otm/03-05b.avif",
          "fallback": "https://betshoptv.com/img/fallback/03-05b.jpg"
        },
        {
          "thumb": "https://betshoptv.com/img/tmb/03-05c.avif",
          "otm": "https://betshoptv.com/img/otm/03-05c.avif",
          "fallback": "https://betshoptv.com/img/fallback/03-05c.jpg"
        }
      ]
    },
    {
      "id": "0306",
      "titulo": "03/06 Stereo System 01",
      "tecnica": "Impressão offset em papel couché transferida para EVA estampado, suporte angular e parafuso.",
      "dimensao": "25 x 16 x 16 cm",
      "preco": 150,
      "status": "disponível",
      "disponivel": true,
      "imagens": [
        {
          "thumb": "https://betshoptv.com/img/tmb/03-06a.avif",
          "otm": "https://betshoptv.com/img/otm/03-06a.avif",
          "fallback": "https://betshoptv.com/img/fallback/03-06a.jpg"
        },
        {
          "thumb": "https://betshoptv.com/img/tmb/03-06b.avif",
          "otm": "https://betshoptv.com/img/otm/03-06b.avif",
          "fallback": "https://betshoptv.com/img/fallback/03-06b.jpg"
        }
      ]
    },
    {
      "id": "0307",
      "titulo": "03/07 Super Telão 01",
      "tecnica": "Impressão offset em papel couché transferida para EVA estampado, tinta acrílica, suporte angular e parafuso.",
      "dimensao": "10 x 7,5 x 5,5 cm",
      "preco": 150,
      "status": "disponível",
      "disponivel": true,
      "imagens": [
        {
          "thumb": "https://betshoptv.com/img/tmb/03-07a.avif",
          "otm": "https://betshoptv.com/img/otm/03-07a.avif",
          "fallback": "https://betshoptv.com/img/fallback/03-07a.jpg"
        },
        {
          "thumb": "https://betshoptv.com/img/tmb/03-07b.avif",
          "otm": "https://betshoptv.com/img/otm/03-07b.avif",
          "fallback": "https://betshoptv.com/img/fallback/03-07b.jpg"
        }
      ]
    },
    {
      "id": "0308",
      "titulo": "03/08 Auto Rádio 02",
      "tecnica": "Impressão offset em papel couché transferida para EVA estampado, chapa união e parafusos.",
      "dimensao": "12,5 x 11,5 x 5 cm",
      "preco": 250,
      "status": "em análise",
      "disponivel": false,
      "imagens": [
        {
          "thumb": "https://betshoptv.com/img/tmb/03-08a.avif",
          "otm": "https://betshoptv.com/img/otm/03-08a.avif",
          "fallback": "https://betshoptv.com/img/fallback/03-08a.jpg"
        },
        {
          "thumb": "https://betshoptv.com/img/tmb/03-08b.avif",
          "otm": "https://betshoptv.com/img/otm/03-08b.avif",
          "fallback": "https://betshoptv.com/img/fallback/03-08b.jpg"
        },
        {
          "thumb": "https://betshoptv.com/img/tmb/03-08c.avif",
          "otm": "https://betshoptv.com/img/otm/03-08c.avif",
          "fallback": "https://betshoptv.com/img/fallback/03-08c.jpg"
        }
      ]
    },
    {
      "id": "0309",
      "titulo": "03/09 Conjunto de som e imagem 01",
      "tecnica": "Impressão offset em papel couché transferida para EVA estampado e presilhas metálicas.",
      "dimensao": "25 x 20,5 x 6,5 cm",
      "preco": 150,
      "status": "disponível",
      "disponivel": true,
      "imagens": [
        {
          "thumb": "https://betshoptv.com/img/tmb/03-09a.avif",
          "otm": "https://betshoptv.com/img/otm/03-09a.avif",
          "fallback": "https://betshoptv.com/img/fallback/03-09a.jpg"
        },
        {
          "thumb": "https://betshoptv.com/img/tmb/03-09b.avif",
          "otm": "https://betshoptv.com/img/otm/03-09b.avif",
          "fallback": "https://betshoptv.com/img/fallback/03-09b.jpg"
        }
      ]
    },
    {
      "id": "0310",
      "titulo": "03/10 Filmadora 01",
      "tecnica": "Impressão offset em papel couché transferida para EVA estampado e parafusos.",
      "dimensao": "27,5 x 24,5 x 4 cm",
      "preco": 150,
      "status": "disponível",
      "disponivel": true,
      "imagens": [
        {
          "thumb": "https://betshoptv.com/img/tmb/03-10a.avif",
          "otm": "https://betshoptv.com/img/otm/03-10a.avif",
          "fallback": "https://betshoptv.com/img/fallback/03-10a.jpg"
        },
        {
          "thumb": "https://betshoptv.com/img/tmb/03-10b.avif",
          "otm": "https://betshoptv.com/img/otm/03-10b.avif",
          "fallback": "https://betshoptv.com/img/fallback/03-10b.jpg"
        },
        {
          "thumb": "https://betshoptv.com/img/tmb/03-10c.avif",
          "otm": "https://betshoptv.com/img/otm/03-10c.avif",
          "fallback": "https://betshoptv.com/img/fallback/03-10c.jpg"
        }
      ]
    },
    {
      "id": "0311",
      "titulo": "03/11 Microcomputador 01",
      "tecnica": "Impressão offset em papel couché transferida para EVA estampado, presilhas metálicas e parafuso. ",
      "dimensao": "23 x 23,5 x 10 cm",
      "preco": 150,
      "status": "disponível",
      "disponivel": true,
      "imagens": [
        {
          "thumb": "https://betshoptv.com/img/tmb/03-11a.avif",
          "otm": "https://betshoptv.com/img/otm/03-11a.avif",
          "fallback": "https://betshoptv.com/img/fallback/03-11a.jpg"
        },
        {
          "thumb": "https://betshoptv.com/img/tmb/03-11b.avif",
          "otm": "https://betshoptv.com/img/otm/03-11b.avif",
          "fallback": "https://betshoptv.com/img/fallback/03-11b.jpg"
        },
        {
          "thumb": "https://betshoptv.com/img/tmb/03-11c.avif",
          "otm": "https://betshoptv.com/img/otm/03-11c.avif",
          "fallback": "https://betshoptv.com/img/fallback/03-11c.jpg"
        }
      ]
    },
    {
      "id": "0312",
      "titulo": "03/12 Microcomputador 02",
      "tecnica": "Impressão offset em papel couché transferida para EVA estampado, tinta acrílica e ganchos.",
      "dimensao": "27 x 20,5 x 3 cm",
      "preco": 250,
      "status": "disponível",
      "disponivel": true,
      "imagens": [
        {
          "thumb": "https://betshoptv.com/img/tmb/03-12a.avif",
          "otm": "https://betshoptv.com/img/otm/03-12a.avif",
          "fallback": "https://betshoptv.com/img/fallback/03-12a.jpg"
        },
        {
          "thumb": "https://betshoptv.com/img/tmb/03-12b.avif",
          "otm": "https://betshoptv.com/img/otm/03-12b.avif",
          "fallback": "https://betshoptv.com/img/fallback/03-12b.jpg"
        },
        {
          "thumb": "https://betshoptv.com/img/tmb/03-12c.avif",
          "otm": "https://betshoptv.com/img/otm/03-12c.avif",
          "fallback": "https://betshoptv.com/img/fallback/03-12c.jpg"
        }
      ]
    },
    {
      "id": "0313",
      "titulo": "03/13 Câmera fotográfica 02",
      "tecnica": "Impressão offset em papel couché transferida para EVA estampado e pregos.",
      "dimensao": "51 x 20,5 x 13 cm",
      "preco": 250,
      "status": "em análise",
      "disponivel": false,
      "imagens": [
        {
          "thumb": "https://betshoptv.com/img/tmb/03-13a.avif",
          "otm": "https://betshoptv.com/img/otm/03-13a.avif",
          "fallback": "https://betshoptv.com/img/fallback/03-13a.jpg"
        },
        {
          "thumb": "https://betshoptv.com/img/tmb/03-13b.avif",
          "otm": "https://betshoptv.com/img/otm/03-13b.avif",
          "fallback": "https://betshoptv.com/img/fallback/03-13b.jpg"
        },
        {
          "thumb": "https://betshoptv.com/img/tmb/03-13c.avif",
          "otm": "https://betshoptv.com/img/otm/03-13c.avif",
          "fallback": "https://betshoptv.com/img/fallback/03-13c.jpg"
        }
      ]
    },
    {
      "id": "0401",
      "titulo": "04/01 TV 01",
      "tecnica": "Impressão offset em papel couché transferida para refugo de EVA e prego.",
      "dimensao": "60 x 20,5 x 4 cm",
      "preco": 1800,
      "status": "disponível",
      "disponivel": true,
      "imagens": [
        {
          "thumb": "https://betshoptv.com/img/tmb/04-01a.avif",
          "otm": "https://betshoptv.com/img/otm/04-01a.avif",
          "fallback": "https://betshoptv.com/img/fallback/04-01a.jpg"
        },
        {
          "thumb": "https://betshoptv.com/img/tmb/04-01b.avif",
          "otm": "https://betshoptv.com/img/otm/04-01b.avif",
          "fallback": "https://betshoptv.com/img/fallback/04-01b.jpg"
        }
      ]
    },
    {
      "id": "0402",
      "titulo": "04/02 Filmadora 02",
      "tecnica": "Impressão offset em papel couché transferida para refugo de EVA",
      "dimensao": "27 x 20,5 x 6 cm",
      "preco": 250,
      "status": "disponível",
      "disponivel": true,
      "imagens": [
        {
          "thumb": "https://betshoptv.com/img/tmb/04-02a.avif",
          "otm": "https://betshoptv.com/img/otm/04-02a.avif",
          "fallback": "https://betshoptv.com/img/fallback/04-02a.jpg"
        },
        {
          "thumb": "https://betshoptv.com/img/tmb/04-02b.avif",
          "otm": "https://betshoptv.com/img/otm/04-02b.avif",
          "fallback": "https://betshoptv.com/img/fallback/04-02b.jpg"
        }
      ]
    },
    {
      "id": "0403",
      "titulo": "04/03 Filmadora 03",
      "tecnica": "Impressão offset em papel couché transferida para refugo de EVA, ",
      "dimensao": "30 x 37 x 7 cm",
      "preco": 400,
      "status": "disponível",
      "disponivel": true,
      "imagens": [
        {
          "thumb": "https://betshoptv.com/img/tmb/04-03a.avif",
          "otm": "https://betshoptv.com/img/otm/04-03a.avif",
          "fallback": "https://betshoptv.com/img/fallback/04-03a.jpg"
        },
        {
          "thumb": "https://betshoptv.com/img/tmb/04-03b.avif",
          "otm": "https://betshoptv.com/img/otm/04-03b.avif",
          "fallback": "https://betshoptv.com/img/fallback/04-03b.jpg"
        },
        {
          "thumb": "https://betshoptv.com/img/tmb/04-03c.avif",
          "otm": "https://betshoptv.com/img/otm/04-03c.avif",
          "fallback": "https://betshoptv.com/img/fallback/04-03c.jpg"
        }
      ]
    },
    {
      "id": "0404",
      "titulo": "04/04 Telão 01",
      "tecnica": "Impressão offset em papel couché transferida para refugo de EVA, braçadeiras e parafusos.",
      "dimensao": "30 x 20,5 x 6,5 cm",
      "preco": 300,
      "status": "disponível",
      "disponivel": true,
      "imagens": [
        {
          "thumb": "https://betshoptv.com/img/tmb/04-04a.avif",
          "otm": "https://betshoptv.com/img/otm/04-04a.avif",
          "fallback": "https://betshoptv.com/img/fallback/04-04a.jpg"
        },
        {
          "thumb": "https://betshoptv.com/img/tmb/04-04b.avif",
          "otm": "https://betshoptv.com/img/otm/04-04b.avif",
          "fallback": "https://betshoptv.com/img/fallback/04-04b.jpg"
        }
      ]
    },
    {
      "id": "0405",
      "titulo": "04/05 Microcomputador 03",
      "tecnica": "Impressão offset em papel couché transferida para refugo de EVA, tinta acrílica, aneis de borracha nitrílica e ganchos.",
      "dimensao": "19 x 37 x 12 cm",
      "preco": 350,
      "status": "disponível",
      "disponivel": true,
      "imagens": [
        {
          "thumb": "https://betshoptv.com/img/tmb/04-05a.avif",
          "otm": "https://betshoptv.com/img/otm/04-05a.avif",
          "fallback": "https://betshoptv.com/img/fallback/04-05a.jpg"
        },
        {
          "thumb": "https://betshoptv.com/img/tmb/04-05b.avif",
          "otm": "https://betshoptv.com/img/otm/04-05b.avif",
          "fallback": "https://betshoptv.com/img/fallback/04-05b.jpg"
        },
        {
          "thumb": "https://betshoptv.com/img/tmb/04-05c.avif",
          "otm": "https://betshoptv.com/img/otm/04-05c.avif",
          "fallback": "https://betshoptv.com/img/fallback/04-05c.jpg"
        },
        {
          "thumb": "https://betshoptv.com/img/tmb/04-05d.avif",
          "otm": "https://betshoptv.com/img/otm/04-05d.avif",
          "fallback": "https://betshoptv.com/img/fallback/04-05d.jpg"
        }
      ]
    },
    {
      "id": "0406",
      "titulo": "04/06 Auto Rádio 03",
      "tecnica": "Impressão offset em papel couché transferida para refugo de EVA, chapa união, arruela e parafusos.",
      "dimensao": "27 x 20 x 6 cm",
      "preco": 300,
      "status": "disponível",
      "disponivel": true,
      "imagens": [
        {
          "thumb": "https://betshoptv.com/img/tmb/04-06a.avif",
          "otm": "https://betshoptv.com/img/otm/04-06a.avif",
          "fallback": "https://betshoptv.com/img/fallback/04-06a.jpg"
        },
        {
          "thumb": "https://betshoptv.com/img/tmb/04-06b.avif",
          "otm": "https://betshoptv.com/img/otm/04-06b.avif",
          "fallback": "https://betshoptv.com/img/fallback/04-06b.jpg"
        },
        {
          "thumb": "https://betshoptv.com/img/tmb/04-06c.avif",
          "otm": "https://betshoptv.com/img/otm/04-06c.avif",
          "fallback": "https://betshoptv.com/img/fallback/04-06c.jpg"
        },
        {
          "thumb": "https://betshoptv.com/img/tmb/04-06d.avif",
          "otm": "https://betshoptv.com/img/otm/04-06d.avif",
          "fallback": "https://betshoptv.com/img/fallback/04-06d.jpg"
        }
      ]
    },
    {
      "id": "0407",
      "titulo": "04/07 Videocassete 01",
      "tecnica": "Impressão offset em papel couché transferida para refugo de EVA, braçadeira e parafusos.",
      "dimensao": "26 x 19 x 5 cm",
      "preco": 250,
      "status": "em análise",
      "disponivel": false,
      "imagens": [
        {
          "thumb": "https://betshoptv.com/img/tmb/04-07a.avif",
          "otm": "https://betshoptv.com/img/otm/04-07a.avif",
          "fallback": "https://betshoptv.com/img/fallback/04-07a.jpg"
        },
        {
          "thumb": "https://betshoptv.com/img/tmb/04-07b.avif",
          "otm": "https://betshoptv.com/img/otm/04-07b.avif",
          "fallback": "https://betshoptv.com/img/fallback/04-07b.jpg"
        },
        {
          "thumb": "https://betshoptv.com/img/tmb/04-07c.avif",
          "otm": "https://betshoptv.com/img/otm/04-07c.avif",
          "fallback": "https://betshoptv.com/img/fallback/04-07c.jpg"
        },
        {
          "thumb": "https://betshoptv.com/img/tmb/04-07d.avif",
          "otm": "https://betshoptv.com/img/otm/04-07d.avif",
          "fallback": "https://betshoptv.com/img/fallback/04-07d.jpg"
        }
      ]
    },
    {
      "id": "0408",
      "titulo": "04/08 Super Telão 02",
      "tecnica": "Impressão offset em papel couché transferida para refugo de EVA e ferragens.",
      "dimensao": "53 x 15 x 3 cm",
      "preco": 250,
      "status": "em análise",
      "disponivel": false,
      "imagens": [
        {
          "thumb": "https://betshoptv.com/img/tmb/04-08a.avif",
          "otm": "https://betshoptv.com/img/otm/04-08a.avif",
          "fallback": "https://betshoptv.com/img/fallback/04-08a.jpg"
        },
        {
          "thumb": "https://betshoptv.com/img/tmb/04-08b.avif",
          "otm": "https://betshoptv.com/img/otm/04-08b.avif",
          "fallback": "https://betshoptv.com/img/fallback/04-08b.jpg"
        },
        {
          "thumb": "https://betshoptv.com/img/tmb/04-08c.avif",
          "otm": "https://betshoptv.com/img/otm/04-08c.avif",
          "fallback": "https://betshoptv.com/img/fallback/04-08c.jpg"
        }
      ]
    },
    {
      "id": "0409",
      "titulo": "04/09 LANLA",
      "tecnica": "EVA Tijolinho",
      "dimensao": "8 x 88 x 8 cm",
      "preco": 888,
      "status": "disponível",
      "disponivel": true,
      "imagens": [
        {
          "thumb": "https://betshoptv.com/img/tmb/04-09a.avif",
          "otm": "https://betshoptv.com/img/otm/04-09a.avif",
          "fallback": "https://betshoptv.com/img/fallback/04-09a.jpg"
        }
      ]
    }
  ],
  "backupUrl": "https://drive.google.com/uc?id=1XPzpwZdDjLKx-6lsQeWalEYKSYBjVC4W"
}